{"meta":{"LastUpdated":"2017-03-09T19:38:33+0000","TotalResults":1,"Agreement":"Use of the APIs and any related data will be subject to the terms of the Open Licence and subject to terms and conditions","License":"https://www.openbanking.org.uk/open-licence","TermsOfUse":"https://www.openbanking.org.uk/terms"},"data":[{"Organisation":{"ParentOrganisation":{"BIC":"BARCGB22","OrganisationName":{"LegalName":"Barclays Bank PLC"}},"Brand":{"TrademarkIPOCode":"EU","TrademarkID":"008757767"}},"ProductName":"BarclayLoan (co.uk)","ProductTypeName":"SmeUnsecuredLoan","ProductURL":["http://www.barclays.co.uk/business-banking/borrow/loans"],"ProductIdentifier":"BBLT","ProductSegment":["Corporate"],"ProductDescription":"Fixed term, Fixed Rate Loan","TsandCs":["http://www.barclays.co.uk/ImportantInformation/Termsandconditions/P1242575350746"],"CustomerAccessChannels":["Branch","Online","Phone","MobileBankingApp"],"Currency":["GBP"],"MinimumLoanTerm":365,"MaximumLoanTerm":3650,"MinimumLoanAmount":"1000.00","MaximumLoanAmount":"25000.00","PaymentHoliday":true,"LoanItem":[{"ProductState":"Regular","CCARegulatedEntity":true,"IsALowInterestRepaymentStartPossible":false,"IsThisAnInterestOnlyLoan":false,"WillTheLoanBePaidInTrancheDrawdowns":false}],"Eligibility":{"AgeRestricted":true,"MinimumAge":18,"OtherFinancialHoldingRequired":false,"Description":"Eligibility for this account depends on you meeting our credit and affordability criteria, including checks we may carry out with credit and fraud prevention agencies.","IncomeTurnoverRelated":true,"ResidencyRestricted":false,"ThirdSectorOrganisations":true,"MinimumOperatingBalanceExists":false,"EligibilityType":"BusinessOnly","PreviousBankruptcy":true},"FeesAndCharges":[{"ProductState":"Regular","Fees":{"FeeDetails":[{"FeeSubType":"Regular","FeeDetail":{"FeeType":"LoanEarlyRepayment","FeeSubDetails":{"FeeFrequency":"PerOccurrence","Negotiable":false,"FeesAndChargesNotes":"If you repay in full or in part, we may charge a fee equal to 30 days' interest based on the amount you repay."}}},{"FeeSubType":"Regular","FeeDetail":{"FeeType":"ServiceCSecurityFee","FeeSubDetails":{"FeeFrequency":"StartOfLoan","FeeAmount":"300.00","Negotiable":false,"FeesAndChargesNotes":"This fee is only charged when a Personal Guarantee is required on an unregulated loan."}}}]}}],"Benefits":{"Benefit":false}}]}